codevariety/PRNG/__init__.py
codevariety/PRNG/prng.py
codevariety/__init__.py
codevariety/debugtracer/__init__.py
codevariety/debugtracer/debug_tracer.py
codevariety/pysvn/__init__.py
codevariety/pysvn/pysvn.py
codevariety/smartset/__init__.py
codevariety/smartset/smartset.py
codevariety-0.1.0.dist-info/LICENSE
codevariety-0.1.0.dist-info/METADATA
codevariety-0.1.0.dist-info/WHEEL
codevariety-0.1.0.dist-info/RECORD
