Metadata-Version: 2.3
Name: codevariety
Version: 0.1.0
Summary: Collection of useful python tools
License: MIT
Keywords: set,custom set,sorted set,data structure,smartset,collection,python
Author: Kyle Simpson
Author-email: Kyle_Simpson5624@yahoo.com
Requires-Python: >=3.8
Classifier: License :: OSI Approved :: MIT License
Classifier: Programming Language :: Python :: 3
Classifier: Programming Language :: Python :: 3.8
Classifier: Programming Language :: Python :: 3.9
Classifier: Programming Language :: Python :: 3.10
Classifier: Programming Language :: Python :: 3.11
Classifier: Programming Language :: Python :: 3.12
Classifier: Programming Language :: Python :: 3.13
